fsm_eigenvalue/__init__.py
fsm_eigenvalue/load.py
fsm_eigenvalue/main.py
fsm_eigenvalue/shell.py
fsm_eigenvalue/store.py
fsm_eigenvalue/compute/__init__.py
fsm_eigenvalue/compute/core.py
fsm_eigenvalue/compute/integral_db.py
fsm_eigenvalue/compute/matrices.py
fsm_eigenvalue/compute/parameter_sweep.py
fsm_eigenvalue/compute/utils.py
fsm_eigenvalue-1.0.1.dist-info/DESCRIPTION.rst
fsm_eigenvalue-1.0.1.dist-info/METADATA
fsm_eigenvalue-1.0.1.dist-info/RECORD
fsm_eigenvalue-1.0.1.dist-info/WHEEL
fsm_eigenvalue-1.0.1.dist-info/entry_points.txt
fsm_eigenvalue-1.0.1.dist-info/metadata.json
fsm_eigenvalue-1.0.1.dist-info/top_level.txt
