Metadata-Version: 2.0
Name: fsm-eigenvalue
Version: 1.0.1
Summary: Console app and Python API implementing a generalization of eigenvalue problem within the harmonic coupled finite strip method, used for parametric modeling of static and dynamic inelastic buckling, free vibration, damage and failure in prismatic shell structures.
Home-page: https://github.com/petarmaric/fsm_eigenvalue
Author: Petar Maric
Author-email: petarmaric@uns.ac.rs
License: BSD
Platform: any
Classifier: Development Status :: 5 - Production/Stable
Classifier: Environment :: Console
Classifier: Intended Audience :: Developers
Classifier: Intended Audience :: Science/Research
Classifier: License :: OSI Approved :: BSD License
Classifier: Operating System :: OS Independent
Classifier: Programming Language :: Python :: 2.7
Classifier: Topic :: Scientific/Engineering
Classifier: Topic :: Scientific/Engineering :: Physics
Requires-Dist: PyYAML (>=3.11,<4.0)
Requires-Dist: beam-integrals (>=1.1,<2.0)
Requires-Dist: networkx (>=1.11,<2.0)
Requires-Dist: numpy (>=1.11,<2.0)
Requires-Dist: physical-dualism (>=1.0,<2.0)
Requires-Dist: requests (<3.0,>=2.18)
Requires-Dist: tables (>=3.2,<4.0)
Requires-Dist: tzlocal (>=1.5,<2.0)
